wechat_webhook/__init__.py
wechat_webhook/plugin.py
sentry_wechat_webhook-0.0.6.dist-info/METADATA
sentry_wechat_webhook-0.0.6.dist-info/WHEEL
sentry_wechat_webhook-0.0.6.dist-info/entry_points.txt
sentry_wechat_webhook-0.0.6.dist-info/top_level.txt
sentry_wechat_webhook-0.0.6.dist-info/RECORD
